windows_wifi_manager/__init__.py
windows_wifi_manager/__main__.py
windows_wifi_manager/display_data.py
windows_wifi_manager/top_level_window.py
windows_wifi_manager/wifi_connection.py
windows_wifi_manager/wifi_data.py
windows_wifi_manager/Data/sampleProfile.xml
windows_wifi_manager/Data/images/check.png
windows_wifi_manager/Data/images/error.png
windows_wifi_manager/Data/images/warning.png
windows_wifi_manager/Data/images/wifi2.ico
windows_wifi_manager-0.2.0.dist-info/LICENSE
windows_wifi_manager-0.2.0.dist-info/METADATA
windows_wifi_manager-0.2.0.dist-info/WHEEL
windows_wifi_manager-0.2.0.dist-info/entry_points.txt
windows_wifi_manager-0.2.0.dist-info/top_level.txt
windows_wifi_manager-0.2.0.dist-info/RECORD
