Metadata-Version: 2.1
Name: windows-wifi-manager
Version: 0.2.0
Summary: Know the saved WiFi details and add WiFi profile using a simple graphical interface in windows.
Home-page: https://github.com/NihalAgarwal/Windows-Wi-Fi-Manager
Author: Nihal Agarwal
Author-email: nihal.agarwal.1426@gmail.com
License: MIT
Keywords: gui,wifi,netsh,Wi-Fi
Platform: UNKNOWN
Classifier: License :: OSI Approved :: MIT License
Classifier: Programming Language :: Python
Classifier: Programming Language :: Python :: 3.7
Classifier: Programming Language :: Python :: 3.8
Classifier: Operating System :: Microsoft :: Windows
Requires-Python: >=3.7
Requires-Dist: appdirs (==1.4.3)
Requires-Dist: lxml (==4.4.2)
Requires-Dist: requests (==2.22.0)
